.gitignore
.travis.yml
LICENSE
MANIFEST.in
Makefile
README.rst
develop.sh
pyproject.toml
requirements.txt
setup.py
docker/Dockerfile
docker/Makefile
docs/Census.rst
docs/GeneratingRowsWithPrograms.rst
docs/GettingStarted.rst
docs/PrivateDatasets.rst
docs/Wrangling packages.rst
examples/Metatab Package.ipynb
examples/Pandas Reporter Example.ipynb
examples/pandas-reporter.py
metatab/__init__.py
metatab/appurl.py
metatab/cli.py
metatab/datapackage.py
metatab/doc.py
metatab/exc.py
metatab/parser.py
metatab/resolver.py
metatab/rowgen.py
metatab/terms.py
metatab/util.py
metatab.egg-info/PKG-INFO
metatab.egg-info/SOURCES.txt
metatab.egg-info/dependency_links.txt
metatab.egg-info/entry_points.txt
metatab.egg-info/requires.txt
metatab.egg-info/top_level.txt
metatab/templates/__init__.py
metatab/templates/datapackage.csv
metatab/templates/metatab.csv
metatab/test/Dockerfile
metatab/test/Makefile
metatab/test/__init__.py
metatab/test/core.py
metatab/test/test_doc.py
metatab/test/test_parser.py
metatab/test/outputs/datapackage.json
metatab/test/outputs/metadata.json
metatab/test/test-data/__init__.py
metatab/test/test-data/almost-everything.csv
metatab/test/test-data/census.csv
metatab/test/test-data/childpropertytype.csv
metatab/test/test-data/children.csv
metatab/test/test-data/children2.csv
metatab/test/test-data/children3.csv
metatab/test/test-data/civicknowledge.com-rcfe_affordability-2015.csv
metatab/test/test-data/datapackage_ex1.csv
metatab/test/test-data/datapackage_ex1_web.csv
metatab/test/test-data/datapackage_ex2.csv
metatab/test/test-data/declare-only.csv
metatab/test/test-data/example1-headers.csv
metatab/test/test-data/example1-web.csv
metatab/test/test-data/example1.csv
metatab/test/test-data/example1.txt
metatab/test/test-data/example2.csv
metatab/test/test-data/geo.csv
metatab/test/test-data/headers.csv
metatab/test/test-data/include1.csv
metatab/test/test-data/include2.csv
metatab/test/test-data/include3.csv
metatab/test/test-data/issue1.csv
metatab/test/test-data/name.csv
metatab/test/test-data/name2.csv
metatab/test/test-data/nested.csv
metatab/test/test-data/programsource.csv
metatab/test/test-data/properties.csv
