Metadata-Version: 2.1
Name: metatab
Version: 0.8.5
Summary: Data format for storing structured data in spreadsheet tables
Home-page: https://github.com/Metatab/metatab-py.git
Author: Eric Busboom
Author-email: eric@civicknowledge.com
License: BSD
Classifier: Development Status :: 4 - Beta
Classifier: Intended Audience :: Developers
Classifier: License :: OSI Approved :: BSD License
Classifier: Operating System :: OS Independent
Classifier: Programming Language :: Python
Classifier: Programming Language :: Python :: 3.6
Classifier: Topic :: Software Development :: Libraries :: Python Modules
Provides-Extra: datapackage
License-File: LICENSE
